bier/__init__.py
bier/EndianedBinaryIO/EndianedBufferedReader.py
bier/EndianedBinaryIO/EndianedBufferedWriter.py
bier/EndianedBinaryIO/EndianedBytesIO.py
bier/EndianedBinaryIO/EndianedFileIO.py
bier/EndianedBinaryIO/EndianedIOBase.py
bier/EndianedBinaryIO/EndianedStreamIO.py
bier/EndianedBinaryIO/__init__.py
bier/EndianedBinaryIO/_structs.py
bier/EndianedBinaryIO/C/EndianedBytesIO.cp310-win_amd64.pyd
bier/EndianedBinaryIO/C/EndianedBytesIO.pyi
bier/EndianedBinaryIO/C/EndianedIOBase.pyi
bier/EndianedBinaryIO/C/EndianedStreamIO.cp310-win_amd64.pyd
bier/EndianedBinaryIO/C/EndianedStreamIO.pyi
bier/EndianedBinaryIO/C/__init__.py
bier/serialization/BinarySerializable.py
bier/serialization/Serializable.py
bier/serialization/TypeNode.py
bier/serialization/__init__.py
bier/serialization/_typing_helpers.py
bier/serialization/builtin_aliases.py
bier/serialization/builtins.py
bier/serialization/options.py
bier-0.0.3.dist-info/licenses/LICENSE
tests/__init__.py
tests/EndianedBinaryIO/EndianedIOTestHelper.py
tests/EndianedBinaryIO/EndianedIO_test.py
tests/EndianedBinaryIO/__init__.py
tests/serialization/TypeNode_test.py
tests/serialization/__init__.py
bier-0.0.3.dist-info/METADATA
bier-0.0.3.dist-info/WHEEL
bier-0.0.3.dist-info/top_level.txt
bier-0.0.3.dist-info/RECORD
