Metadata-Version: 2.4
Name: bier
Version: 0.0.3
Summary: Endian-aware binary IO streams and annotation driven serialization helpers
Author-email: Rudolf Kolbe <rkolbe96@gmail.com>
License: MIT
Project-URL: Homepage, https://github.com/K0lb3/Binaryhelper
Project-URL: Bug Tracker, https://github.com/K0lb3/Binaryhelper/issues
Classifier: Operating System :: OS Independent
Classifier: Intended Audience :: Developers
Classifier: Programming Language :: Python
Classifier: Programming Language :: Python :: 3
Classifier: Programming Language :: Python :: 3.8
Classifier: Programming Language :: Python :: 3.9
Classifier: Programming Language :: Python :: 3.10
Classifier: Programming Language :: Python :: 3.11
Classifier: Programming Language :: Python :: 3.12
Classifier: Programming Language :: Python :: 3.13
Classifier: Programming Language :: Python :: 3.14
Classifier: Topic :: Software Development :: Libraries :: Python Modules
Requires-Python: >=3.8
License-File: LICENSE
Requires-Dist: typing-extensions>=4.6; python_version >= "3.8" and python_version < "3.12"
Provides-Extra: tests
Requires-Dist: pytest; extra == "tests"
Provides-Extra: dev
Requires-Dist: ruff; extra == "dev"
Requires-Dist: pre-commit; extra == "dev"
Requires-Dist: bier[tests]; extra == "dev"
Dynamic: license-file
